Workbook
Name aporte: 'Simulador FII'!$D$16
Name patrimonio: 'Simulador FII'!$D$19
Name qtd_anos: 'Simulador FII'!$D$17
Name rendimento_carteira: 'Simulador FII'!$D$12
Name salario: 'Simulador FII'!$D$11
Name sugestao_investimento: 'Simulador FII'!$D$13
Name taxa_mensal: 'Simulador FII'!$D$18

Sheet Simulador FII
B10: Configurações
B11: Renda Mensal | D11: 2000
B12: Rendimento Carteira | D12: 0.009
B13: Aporte Mensal Sugerido (30% da Renda Mensal) | D13: =salario*30% -> 600
B15: Investimento Mensal
B16: Quanto deseja investir por mês? | D16: 600
B17: Por quanto tempo? (anos) | D17: 5
B18: Qual taxa de rendimento mensal deseja simular? | D18: 0.01079
B19: Patrimônio acumulado? | D19: =FV(taxa_mensal,qtd_anos*12,aporte*-1) -> 50266.148
B20: Dividendos mensais? | D20: =patrimonio*rendimento_carteira -> 452.39534
B21: *Os valores apresentados são estimativas educacionais e não representam garantia de retorno.
B22: Cenários | C22: Patrimônio | D22: Dividendo
B23: Quanto em 2 anos? | C23: =FV(taxa_mensal,2*12,aporte*-1) -> 16336.576 | D23: =C23*rendimento_carteira -> 147.02919
B24: Quanto em 5 anos? | C24: =FV(taxa_mensal,5*12,aporte*-1) -> 50266.148 | D24: =C24*rendimento_carteira -> 452.39534
B25: Quanto em 10 anos? | C25: =FV(taxa_mensal,10*12,aporte*-1) -> 145970.53 | D25: =C25*rendimento_carteira -> 1313.7347
B26: Quanto em 15 anos? | C26: =FV(taxa_mensal,15*12,aporte*-1) -> 328187.16 | D26: =C26*rendimento_carteira -> 2953.6844
B27: Quanto em 20 anos? | C27: =FV(taxa_mensal,20*12,aporte*-1) -> 675119.04 | D27: =C27*rendimento_carteira -> 6076.0714
B29: MINHA META DE RENDA
B30: Minha meta de renda mensal: | C30: 3000
B31: Taxa de dividendos mensais | C31: 0.009
B32: Patrimônio necessário: | C32: =IFERROR(C30/C31,0) -> 333333.33
B33: Patrimônio projetado: | C33: =patrimonio -> 50266.148
B34: Quanta falta para alcançar a meta? | C34: =MAX(C32-C33) -> 283067.18
B35: Percentual alcançado: | C35: =IFERROR(C33/C32,0) -> 0.15079845
C36: Clique aqui para selecionar!
B37: Perfil | C37: Agressivo
B38: Valor a ser investido por mês | C38: =aporte -> 600
B40: TIPO DE FII | C40: PERCENTUAL SUGERIDO | D40: VALORES
B41: Papel | C41: =VLOOKUP($C$37&"-"&B41,Apoio!B3:E21,4,FALSE) -> 0.5 | D41: =C41*$C38 -> 300
B42: Tijolo | C42: =VLOOKUP($C$37&"-"&B42,Apoio!B4:E22,4,FALSE) -> 0.1 | D42: =C42*C38 -> 60
B43: Híbridos | C43: =VLOOKUP($C$37&"-"&B43,Apoio!B5:E23,4,FALSE) -> 0.05 | D43: =C43*C38 -> 30
B44: FOFs | C44: =VLOOKUP($C$37&"-"&B44,Apoio!B6:E24,4,FALSE) -> 0.05 | D44: =C44*C38 -> 30
B45: Desenvolvimento | C45: =VLOOKUP($C$37&"-"&B45,Apoio!B7:E25,4,FALSE) -> 0.2 | D45: =C45*C38 -> 120
B46: Hotelarias | C46: =VLOOKUP($C$37&"-"&B46,Apoio!B8:E26,4,FALSE) -> 0.1 | D46: =C46*C38 -> 60
B47: TOTAL | D47: =SUM(D41:D46) -> 600

Sheet Apoio
B3: CHAVE | C3: PERFIL | D3: TIPO DE FII | E3: %
B4: =C4&"-"&D4 -> Conservador-Papel | C4: Conservador | D4: Papel | E4: 0.3 | H4: %
B5: =C5&"-"&D5 -> Conservador-Tijolo | C5: Conservador | D5: Tijolo | E5: 0.5 | G5: Moderado-Tijolo | H5: =VLOOKUP(G5,B3:E21,4,FALSE) -> 0.35
B6: =C6&"-"&D6 -> Conservador-Híbridos | C6: Conservador | D6: Híbridos | E6: 0.1
B7: =C7&"-"&D7 -> Conservador-FOFs | C7: Conservador | D7: FOFs | E7: 0.1
B8: =C8&"-"&D8 -> Conservador-Desenvolvimento | C8: Conservador | D8: Desenvolvimento | E8: 0
B9: =C9&"-"&D9 -> Conservador-Hotelarias | C9: Conservador | D9: Hotelarias | E9: 0
B10: =C10&"-"&D10 -> Moderado-Papel | C10: Moderado | D10: Papel | E10: 0.32
B11: =C11&"-"&D11 -> Moderado-Tijolo | C11: Moderado | D11: Tijolo | E11: 0.35
B12: =C12&"-"&D12 -> Moderado-Híbridos | C12: Moderado | D12: Híbridos | E12: 0.08
B13: =C13&"-"&D13 -> Moderado-FOFs | C13: Moderado | D13: FOFs | E13: 0.05
B14: =C14&"-"&D14 -> Moderado-Desenvolvimento | C14: Moderado | D14: Desenvolvimento | E14: 0.1
B15: =C15&"-"&D15 -> Moderado-Hotelarias | C15: Moderado | D15: Hotelarias | E15: 0.1
B16: =C16&"-"&D16 -> Agressivo-Papel | C16: Agressivo | D16: Papel | E16: 0.5
B17: =C17&"-"&D17 -> Agressivo-Tijolo | C17: Agressivo | D17: Tijolo | E17: 0.1
... B21: =C21&"-"&D21 -> Agressivo-Hotelarias | C21: Agressivo | D21: Hotelarias | E21: 0.1
